mplexable/__init__.py
mplexable/_version.py
mplexable/afsub.py
mplexable/basic.py
mplexable/codex.py
mplexable/config.py
mplexable/configure.py
mplexable/feat.py
mplexable/imgmeta.py
mplexable/keypointregist.py
mplexable/mics.py
mplexable/muxplt.py
mplexable/ometiff.py
mplexable/regist.py
mplexable/sane.py
mplexable/segment.py
mplexable/stitch.py
mplexable/thresh.py
mplexable/util.py
mplexable/src/template_afsubtraction_slidepxscene.py
mplexable/src/template_crop_mscene.py
mplexable/src/template_exposuretimecorrect_slidepxscene.py
mplexable/src/template_extractfeatures_slide.py
mplexable/src/template_featurecorrectlabels_slide.py
mplexable/src/template_filterfeatures_slide.py
mplexable/src/template_micspatch_slide.py
mplexable/src/template_micstrafo_batch.py
mplexable/src/template_nuccellzprojlabel_slide.py
mplexable/src/template_ometiff_slidepxscene.py
mplexable/src/template_registration_mscene.m
mplexable/src/template_registration_mscene.py
mplexable/src/template_segmentation_match.py
mplexable/src/template_segmentation_nuccell.py
mplexable/src/template_thresh_slide.py
mplexable/src/template_vizrawimage_slide.py
mplexable/src/template_vizregimage_slide.py
mplexable/src/template_xzcompress_slide.py
mplexable/src/template_xzdecompress_slide.py
mplexable-1.0.3.dist-info/LICENSE
mplexable-1.0.3.dist-info/METADATA
mplexable-1.0.3.dist-info/WHEEL
mplexable-1.0.3.dist-info/top_level.txt
mplexable-1.0.3.dist-info/RECORD
